[
    {
        "title": "Đăng nhập",
        "module": "lock",
        "moduleName": "Bảo mật",
        "action": "login",
        "actionName": "Đăng nhập",
        "icon": ""
    },
    {
        "title": "Đăng ký",
        "module": "lock",
        "moduleName": "Bảo mật",
        "action": "register",
        "actionName": "Đăng ký",
        "icon": ""
    },
    {
        "title": "Màng hình khóa",
        "module": "lock",
        "moduleName": "Bảo mật",
        "action": "index",
        "actionName": "Màng hình khóa",
        "icon": ""
    },
    {
        "title": "Màng hình bảo trì",
        "module": "lock",
        "moduleName": "Bảo mật",
        "action": "maintenance",
        "actionName": "Màng hình bảo trì",
        "icon": ""
    },
    {
        "title": "Quên mật khẩu",
        "module": "lock",
        "moduleName": "Bảo mật",
        "action": "forgot-password",
        "actionName": "Quên mật khẩu",
        "icon": ""
    },
    {
        "title": "Tài khoản",
        "module": "profile",
        "moduleName": "Tài khoản",
        "action": "index",
        "actionName": "Tài khoản",
        "icon": "icon-user"
    },
    {
        "title": "Hỗ trợ",
        "module": "ticket",
        "moduleName": "Hỗ trợ",
        "action": "index",
        "actionName": "Hỗ trợ",
        "icon": "fa fa-support"
    },
    {
        "title": "Cài đặt",
        "module": "setting",
        "moduleName": "Cài đặt",
        "action": "index",
        "actionName": "Cài đặt",
        "icon": "icon-settings"
    },
    {
        "title": "Trò chuyện",
        "module": "chat",
        "moduleName": "Trò chuyện",
        "action": "index",
        "actionName": "Trò chuyện",
        "icon": "fa fa-comments"
    },
    {
        "title": "Tìm kiếm",
        "module": "search",
        "moduleName": "Tìm kiếm",
        "action": "index",
        "actionName": "Tìm kiếm",
        "icon": "fa fa-comments"
    },
    {
        "title": "Lịch sử Domain",
        "module": "histories",
        "moduleName": "Lịch sử",
        "action": "domain",
        "actionName": "Lịch sử Domain",
        "icon": "fa fa-comments"
    },
    {
        "title": "Lịch sử Hosting",
        "module": "histories",
        "moduleName": "Lịch sử",
        "action": "hosting",
        "actionName": "Lịch sử Hosting",
        "icon": "fa fa-comments"
    }
]